tweakpane/__init__.py
tweakpane/index.js
tweakpane-0.2.0.dist-info/METADATA
tweakpane-0.2.0.dist-info/WHEEL
tweakpane-0.2.0.dist-info/licenses/LICENSE
tweakpane-0.2.0.dist-info/RECORD
