Metadata-Version: 2.1
Name: tweakpane
Version: 0.2.0
Summary: Python bindings for Tweakpane UI
Project-URL: Documentation, https://github.com/manzt/ipytweakpane#readme
Project-URL: Issues, https://github.com/manzt/ipytweakpane/issues
Project-URL: Source, https://github.com/manzt/ipytweakpane
Author-email: Trevor Manz <trevor.j.manz@gmail.com>
License: MIT
License-File: LICENSE
Classifier: Development Status :: 4 - Beta
Classifier: Programming Language :: Python
Classifier: Programming Language :: Python :: 3.7
Classifier: Programming Language :: Python :: 3.8
Classifier: Programming Language :: Python :: 3.9
Classifier: Programming Language :: Python :: 3.10
Classifier: Programming Language :: Python :: 3.11
Requires-Python: >=3.7
Requires-Dist: anywidget>=0.9.2
